guardian_sdk/__init__.py
guardian_sdk/client.py
guardian_securitysdk-0.2.1.dist-info/METADATA
guardian_securitysdk-0.2.1.dist-info/WHEEL
guardian_securitysdk-0.2.1.dist-info/top_level.txt
guardian_securitysdk-0.2.1.dist-info/RECORD
