Metadata-Version: 2.4
Name: guardian-securitysdk
Version: 0.2.1
Summary: Guardian SDK for Python
Home-page: https://github.com/SoorajNairA/Guardian-v0.1
Author: Guardian
License: MIT
Requires-Python: >=3.8
Requires-Dist: httpx<0.28.0,>=0.27.0
Requires-Dist: structlog<24.0.0,>=23.1.0
Requires-Dist: tenacity<9.0.0,>=8.2.0
Requires-Dist: typing-extensions>=4.0.0
Dynamic: author
Dynamic: description
Dynamic: description-content-type
Dynamic: home-page
Dynamic: license
Dynamic: requires-dist
Dynamic: requires-python
Dynamic: summary
